aio/run/runner/__init__.py
aio/run/runner/abstract.py
aio/run/runner/decorators.py
aio/run/runner/py.typed
aio/run/runner/runner.py
aio.run.runner-0.3.4.dist-info/METADATA
aio.run.runner-0.3.4.dist-info/WHEEL
aio.run.runner-0.3.4.dist-info/namespace_packages.txt
aio.run.runner-0.3.4.dist-info/top_level.txt
aio.run.runner-0.3.4.dist-info/RECORD
