Metadata-Version: 2.1
Name: aio.run.runner
Version: 0.3.4
Summary: "Async runner definitions"
Home-page: https://github.com/envoyproxy/toolshed/tree/main/aio.run.runner
Author: Ryan Northey
Author-email: ryan@synca.io
Maintainer: Ryan Northey
Maintainer-email: ryan@synca.io
License: Apache Software License 2.0
Requires-Python: >=3.10.0
Requires-Dist: abstracts (>=0.0.12)
Requires-Dist: aio.core (>=0.10.5)
Requires-Dist: coloredlogs
Requires-Dist: frozendict
Requires-Dist: uvloop
Requires-Dist: verboselogs
